Workbook
Name for: [1]SoFP!$B$42

Sheet Weighted Value
B2: ='DCF Value'!B2 -> Simple Energy Private Limited
B4: Particulars | C4: Value | D4: Weight | E4: Weighted Value
B5: DCF Value | C5: ='DCF Value'!C40 -> #REF! | D5: 0 | E5: =C5*D5 -> #REF!
B6: Market Value | C6: =#REF! -> #REF! | D6: 0.5 | E6: =C6*D6 -> #REF!
B7: Book Value | C7: =#REF! -> #REF! | D7: 0.5 | E7: =C7*D7 -> #REF!
E8: =SUM(E5:E7) -> #REF!

Sheet DCF Value
B2: ='Historical SOPL'!B2:F2 -> Simple Energy Private Limited
B3: DCF Valuation
B5: Particulars | C5: =[2]SOPL!E8 -> 2082-83 | D5: =[2]SOPL!F8 -> 2083-84 | E5: =[2]SOPL!G8 -> 2084-85 | F5: =[2]SOPL!H8 -> 2085-86 | G5: =[2]SOPL!I8 -> 2086-87
B6: Net Profit | C6: =#REF! -> #REF! | D6: =#REF! -> #REF! | E6: =#REF! -> #REF! | F6: =#REF! -> #REF! | G6: =#REF! -> #REF!
B7: Interest tax savings [@18% tax rate] | C7: =#REF!*(1-18%) -> #REF! | D7: =#REF!*(1-18%) -> #REF! | E7: =#REF!*(1-18%) -> #REF! | F7: =#REF!*(1-18%) -> #REF! | G7: =#REF!*(1-18%) -> #REF!
B8: Depreciation | C8: =#REF! -> #REF! | D8: =#REF! -> #REF! | E8: =#REF! -> #REF! | F8: =#REF! -> #REF! | G8: =#REF! -> #REF!
B9: CapEX (𝚫) | C9: =#REF! -> #REF! | D9: =#REF! -> #REF! | E9: =#REF! -> #REF! | F9: =#REF! -> #REF! | G9: =#REF! -> #REF!
B10: Working Capital changes | C10: =(#REF!-#REF!)-(#REF!-#REF!) -> #REF! | D10: =(#REF!-#REF!)-(#REF!-#REF!) -> #REF! | E10: =(#REF!-#REF!)-(#REF!-#REF!) -> #REF! | F10: =(#REF!-#REF!)-(#REF!-#REF!) -> #REF! | G10: =(#REF!-#REF!)-(#REF!-#REF!) -> #REF!
B11: Free Cash Flow to Company | C11: =SUM(C6:C10) -> #REF! | D11: =SUM(D6:D10) -> #REF! | E11: =SUM(E6:E10) -> #REF! | F11: =SUM(F6:F10) -> #REF! | G11: =SUM(G6:G10) -> #REF!
B13: Year Factor | C13: 1 | D13: =C13+1 -> 2 | E13: =D13+1 -> 3 | F13: =E13+1 -> 4 | G13: =F13+1 -> 5
B14: Discount Rate | C14: =C22 -> 0.13 | D14: =C14 -> 0.13 | E14: =D14 -> 0.13 | F14: =E14 -> 0.13 | G14: =F14 -> 0.13
B15: PVF | C15: =1/(1+C14)^C13 -> 0.88495575 | D15: =1/(1+D14)^D13 -> 0.78314668 | E15: =1/(1+E14)^E13 -> 0.69305016 | F15: =1/(1+F14)^F13 -> 0.61331873 | G15: =1/(1+G14)^G13 -> 0.54275994
B16: Present Values based on WACC | C16: =C11*C15 -> #REF! | D16: =D11*D15 -> #REF! | E16: =E11*E15 -> #REF! | F16: =F11*F15 -> #REF! | G16: =G11*G15 -> #REF!
B19: Enterprise Values - Perpetuity Growth Method
B21: Free Cash Flow at terminal year of projection | C21: =G11 -> #REF!
B22: WACC | C22: 0.13
B23: Perpetuity Growth Rate | C23: 0.03
B25: Perpetuity Value at End of Year 10 | C25: =(C21*(1+C23))/(C22-C23) -> #REF!
B27: Present Value of Perpetuity | C27: =C25*G15 -> #REF!
B28: (+) Present Value of Free Cash Flows | C28: =SUM(C16:G16) -> #REF!
B29: Enterprise Value | C29: =(C27+C28) -> #REF!
B31: (+) Short Term Debt | C31: 1750000000
B32: (+) Long Term Debt | C32: =#REF! -> #REF!
B33: (-) Cash & Marketable Securities (in millions) | C33: =-#REF! -> #REF!
B34: (-) Net Debt | C34: =SUM(C31:C33) -> #REF!
B35: (-) Preferred and Minority Interest | C35: 0
B36: (=) Equity Value | C36: =C29-C34 -> #REF!
B37: Less: Additional Investment | C37: 600000000
B38: Pre-Money Valuation | C38: =C36-C37 -> #REF!
B39: No of shares pre-money | C39: =(#REF!+#REF!)/100 -> #REF!
B40: Estimated Value per Share Pre-money | C40: =C38/C39 -> #REF!

Sheet Historical SOPL
B2: ='Historical SOFP'!B1:F1 -> Simple Energy Private Limited
B3: Statement of Profit & Loss | H3: Revenue | I3: FY 2080/81 | J3: FY 2081/82
H4: Electricity Sales | I4: 27287025 | J4: 37420261
B5: Particulars | C5: Audited | D5: Audited | E5: Audited | F5: Provisional | H5: System Sales | J5: 86541615
C6: 26.303797 | D6: FY 2079/80 | E6: FY 2080/81 | F6: FY 2081/82 | H6: AMC Income | J6: 280000
B7: Gross Sales/Revenue/Income | C7: 0 | D7: 10468343 | E7: 27287025 | F7: 124241876 | H7: Total | I7: =SUM(I4:I6) -> 27287025 | J7: 124241876
B8: Cost of system sales | C8: 0 | D8: 1136455 | E8: 0 | F8: 55998790
B9: Gross Profit/(Loss) from Trading | C9: =C7-C8 -> 0 | D9: =D7-D8 -> 9331888 | E9: =E7-E8 -> 27287025 | F9: =F7-F8 -> 68243086 | H9: Cost | I9: FY 2080/81 | J9: FY 2081/82
B10: Other Income | C10: 3960895 | D10: 4348983 | E10: 7451383 | F10: 5896212 | H10: Electricity Sales | I10: 1700681 | J10: 2060597
B11: Operation Cost | E11: 1700681 | F11: 2060597 | H11: System Sales | J11: 55998790
B12: Employee Benefits | E12: 549577 | F12: 4146110 | H12: AMC Income
B13: Administration Expenditure | C13: 8248205 | D13: 8566576 | E13: 1636739 | F13: 2985254 | H13: Total | I13: =SUM(I10:I12) -> 1700681 | J13: =SUM(J10:J12) -> 58059387
B14: Earnings Before Interest Deprecviation & Tax (EBITDA) | C14: =C9+C10-SUM(C11:C13) -> -4287310 | D14: =D9+D10-SUM(D11:D13) -> 5114295 | E14: =E9+E10-SUM(E11:E13) -> 30851411 | F14: =F9+F10-SUM(F11:F13) -> 64947337
B15: Interest | C15: 0 | D15: 0 | F15: 0 | I15: =I10/I4 -> 0.062325629 | J15: =J10/J4 -> 0.055066345
B16: Depreciation | C16: 4717697 | D16: 10816924 | E16: 20354862 | F16: 26502367
B17: Net Profit before Tax | C17: =C14-C15-C16 -> -9005007 | D17: =D14-D15-D16 -> -5702629 | E17: =E14-E15-E16 -> 10496549 | F17: =F14-F15-F16 -> 38444970
B18: Income Tax | E18: 3924757 | F18: 6041958
B19: Defered Tax (Income)/Expenses | D19: 0 | F19: 6179594
B20: Net Profit After Tax | C20: =C17-C18+C19 -> -9005007 | D20: =D17-D18+D19 -> -5702629 | E20: =E17-E18+E19 -> 6571792 | F20: =F17-F18+F19 -> 38582606

Sheet Historical SOFP
B1: Simple Energy Private Limited
B2: Statement of Financial Position
B4: Particulars | C4: Audited | D4: Provision | E4: Audited | F4: Provisional
C5: FY 2078/79 | D5: FY 2079/80 | E5: FY 2080/81 | F5: FY 2081/82
B6: Non Current Assets
B7: Capital WIP | C7: 101898171 | D7: 18730699 | E7: 27804533 | F7: 324652
B8: PPE | C8: 2127387 | D8: 2382268 | E8: 2636134 | F8: 2707134
B9: Intangible Assets | C9: 22118504 | D9: 22653039 | E9: 22653039 | F9: 22797448
B10: Projct Assets | D10: 158831896 | E10: 228552569 | F10: 295849197
B11: Less: Accumulated Depreciation | C11: -4717696 | D11: -15502027 | E11: -35856890 | F11: -62359256
B12: Deferred Tax Assets | E12: 0 | F12: 6179594
B13: Total Non Current Assets | C13: =SUM(C7:C11) -> 121426366 | D13: =SUM(D7:D11) -> 187095875 | E13: =SUM(E7:E12) -> 245789385 | F13: =SUM(F7:F12) -> 265498769
B14: Inventory
B15: Sundry Debtors | C15: 2819216 | D15: 5164291 | E15: 14755092 | F15: 57005027
B16: Cash & Bank Balances | C16: 4150743 | D16: 6607010 | E16: 10287848 | F16: 69824489
B17: Investment | C17: 300000 | D17: 35300000 | E17: 80300000 | F17: 300000
B18: Other Assets
B19: Current Tax Assets
B20: Total Current Assets | C20: =SUM(C15:C19) -> 7269959 | D20: =SUM(D15:D19) -> 47071301 | E20: =SUM(E14:E19) -> 105342940 | F20: =SUM(F14:F19) -> 127129516
B21: Total Assets | C21: =C13+C20 -> 128696325 | D21: =D13+D20 -> 234167176 | E21: =E13+E20 -> 351132325 | F21: =F13+F20 -> 392628285
B23: Non Current Liabilities
B24: Financial Liabilities
B25: Total | C25: =SUM(C24) -> 0 | D25: =SUM(D24) -> 0 | E25: =SUM(E24) -> 0 | F25: =SUM(F24) -> 0
B26: Current Liabilities
B27: Trade Payables | C27: 17736331 | D27: 2909811 | E27: 2934414 | F27: 3730554
B28: Provisions | E28: 3924747 | F28: 6041958
B29: Current Tax Liabilities
B30: Total Current Liabilities | C30: =SUM(C27:C29) -> 17736331 | D30: =SUM(D27:D29) -> 2909811 | E30: =SUM(E27:E29) -> 6859161 | F30: =SUM(F27:F29) -> 9772512
B31: CAPITAL AND LIABILITIES
B32: Share Capital A/c | C32: 120000000 | D32: 246000000 | E32: 352444000 | F32: 352444000
B33: Share Application | C33: 0
B34: Retained Earnings | C34: -9040006 | D34: -14742636 | E34: -8170834 | F34: 30411774
B35: Reserves | C35: 0 | D35: 0
B36: Total Equity | C36: =SUM(C32:C35) -> 110959994 | D36: =SUM(D32:D35) -> 231257364 | E36: =SUM(E32:E35) -> 344273166 | F36: =SUM(F32:F35) -> 382855774
B38: Total Equity + Liabilities | C38: =C36+C30+C25 -> 128696325 | D38: =D36+D30+D25 -> 234167175 | E38: =E36+E30+E25 -> 351132327 | F38: =F36+F30+F25 -> 392628286
C40: =C38-C21 -> 0 | D40: =D38-D21 -> -1 | E40: =E38-E21 -> 2 | F40: =F38-F21 -> 1

Sheet Projections
B2: Operational Projections
B3: Details | C3: Unit | D3: Till 2025 | E3: Till 2026 | F3: 2027 | G3: =F3+1 -> 2028 | H3: =G3+1 -> 2029 | I3: =H3+1 -> 2030 | J3: Remarks
B4: OPEX/RESCO | C4: MWp | D4: 7.3 | E4: 11 | F4: 15 | G4: 19 | H4: 23 | I4: 25
B5: CAPEX | C5: MWp | D5: 2.5 | E5: 4.5 | F5: 7 | G5: 10 | H5: 13 | I5: 15
B6: BESS | C6: KWh | D6: 0 | E6: 200 | F6: 600 | G6: 1000 | H6: 1500 | I6: 2000 | J6: Currently Under procurement
B7: Ground Mounted | C7: MWp | D7: 0 | E7: 0 | F7: 5 | G7: 15 | H7: 25 | I7: 35 | J7: Net Simple Energy Equiry Basis
B8: AMC | C8: MWp | D8: 1.4 | E8: 2 | F8: 3 | G8: 4.5 | H8: 6 | I8: 7
B9: Energy Efficiency | C9: No | D9: 0 | E9: 1 | F9: 3 | G9: 7 | H9: 11 | I9: 16
B10: L-REC | C10: Mt CP2 reduction | D10: 0 | E10: 1000 | F10: 5000 | G10: 9000 | H10: 14000 | I10: 20000 | J10: Currently in agreement stage
B12: Revenue projection
B13: Details | D13: 2025 | E13: 2026 | F13: 2027 | G13: 2028 | H13: 2029 | I13: 2030 | J13: Remarks
B14: OPEX / RESCO | D14: 39968000 | E14: 60225000 | F14: 82125000 | G14: 104025000 | H14: 125925000 | I14: 136875000
B15: CAPEX | D15: 100000000 | E15: 80000000 | F15: 100000000 | G15: 120000000 | H15: 120000000 | I15: 80000000 | J15: Annual incremental capacity
B16: BESS – Sales Revenue | D16: 0 | E16: 1400000 | F16: 4200000 | G16: 7000000 | H16: 10500000 | I16: 14000000
B17: Ground Mounted | D17: 0 | E17: 0 | F17: 0 | G17: 0 | H17: 5250000 | I17: 22050000 | J17: Long-term investment – dividend
B18: AMC | D18: 1680000 | E18: 2400000 | F18: 3600000 | G18: 5400000 | H18: 7200000 | I18: 8400000
B19: Energy Efficiency | D19: 0 | E19: 500000 | F19: 1500000 | G19: 3500000 | H19: 5500000 | I19: 8000000 | J19: Mainly grant-based projects
B20: I-REC | D20: 0 | E20: 144000 | F20: 742000 | G20: 1335000 | H20: 1869000 | I20: 2373000 | J20: Currently in agreement stage
B21: Total Cash In-Flow | D21: =SUM(D14:D20) -> 141648000 | E21: =SUM(E14:E20) -> 144669000 | F21: =SUM(F14:F20) -> 192167000 | G21: =SUM(G14:G20) -> 241260000 | H21: =SUM(H14:H20) -> 276244000 | I21: =SUM(I14:I20) -> 271698000
B23: Costs/investments projection
B24: Details | D24: 2025 | E24: 2026 | F24: 2027 | G24: 2028 | H24: 2029 | I24: 2030 | J24: Remarks
B25: OPEX / RESCO – operation | D25: 3650000 | E25: 5500000 | F25: 7500000 | G25: 9500000 | H25: 11500000 | I25: 12500000
B26: CAPEX | D26: 75000000 | E26: 68000000 | F26: 85000000 | G26: 102000000 | H26: 102000000 | I26: 68000000 | J26: Annual incremental capacity
B27: BESS | D27: 0 | E27: 200000 | F27: 600000 | G27: 1000000 | H27: 1500000 | I27: 2000000
B28: Ground Mounted – investment | D28: 0 | E28: – | F28: 105000000 | G28: 210000000 | H28: 210000000 | I28: 210000000 | J28: Long-term investment in companies
B29: AMC | D29: 840000 | E29: 1200000 | F29: 1800000 | G29: 2700000 | H29: 3600000 | I29: 4200000
B30: Energy Efficiency | D30: 0 | E30: 300000 | F30: 900000 | G30: 2100000 | H30: 3300000 | I30: 4800000
B31: I-REC | D31: 0 | E31: 29000 | F31: 148000 | G31: 267000 | H31: 374000 | I31: 475000
B32: Total Cash Outflow | D32: =SUM(D25:D31) -> 79490000 | E32: =SUM(E25:E31) -> 75229000 | F32: =SUM(F25:F31) -> 200948000 | G32: =SUM(G25:G31) -> 327567000 | H32: =SUM(H25:H31) -> 332274000 | I32: =SUM(I25:I31) -> 301975000
B34: Assets and Investments – Projections
B35: Details | C35: Unit | D35: 2025 | E35: 2026 | F35: 2027 | G35: 2028 | H35: 2029 | I35: 2030 | J35: Remarks
B36: OPEX/RESCO Projects | C36: NPR'000 | D36: 401500 | E36: 576895 | F36: 784617 | G36: 990077 | H36: 1195695 | I36: 1291301 | J36: Cumulative-Net of depreciation
B37: BESS | C37: NPR'000 | E37: 11000 | F37: 32230 | G37: 52744 | H37: 78808 | I37: 104483 | J37: Investment in Assets- net of grant
B38: Ground Mounted | C38: NPR'000 | F38: 105000 | G38: 315000 | H38: 525000 | I38: 735000 | J38: Equity Investment-Cumulative
B39: Total | D39: =SUM(D36:D38) -> 401500 | E39: =SUM(E36:E38) -> 587895 | F39: =SUM(F36:F38) -> 921847 | G39: =SUM(G36:G38) -> 1357821 | H39: =SUM(H36:H38) -> 1799503 | I39: =SUM(I36:I38) -> 2130784

Sheet Projected FS
B2: Operational (P/L) Projections | D2: 2025 | E2: 2026 | F2: 2027 | G2: 2028 | H2: 2029 | I2: 2030 | J2: Remarks
B3: Details
B4: Revenue
B5: Revenue from OPEX | D5: 39968000 | E5: 60225000 | F5: 82125000 | G5: 104025000 | H5: 125925000 | I5: 136875000
B6: Revenue from CAPEX | D6: 100000000 | E6: 80000000 | F6: 100000000 | G6: 120000000 | H6: 120000000 | I6: 80000000 | J6: Annual incremental capacity
B7: BESS-Revenue | D7: 0 | E7: 1400000 | F7: 4200000 | G7: 7000000 | H7: 10500000 | I7: 14000000 | J7: Battery Energy Storage System. I
B8: Ground Mounted-Dividend | D8: 0 | E8: 0 | F8: 0 | G8: 0 | H8: 5250000 | I8: 22050000 | J8: Long-term investment – dividend
B9: AMC-Revenue | D9: 1680000 | E9: 2400000 | F9: 3600000 | G9: 5400000 | H9: 7200000 | I9: 8400000
B10: Energy Efficiency Revenue | D10: 0 | E10: 500000 | F10: 1500000 | G10: 3500000 | H10: 5500000 | I10: 8000000 | J10: Mainly grant-based projects
B11: IREC Revenue | D11: 0 | E11: 144000 | F11: 742000 | G11: 1335000 | H11: 1869000 | I11: 2373000 | J11: Currently in agreement stage
B12: Total Revenue | D12: =SUM(D5:D11) -> 141648000 | E12: =SUM(E5:E11) -> 144669000 | F12: =SUM(F5:F11) -> 192167000 | G12: =SUM(G5:G11) -> 241260000 | H12: =SUM(H5:H11) -> 276244000 | I12: =SUM(I5:I11) -> 271698000 | J12: =SUM(J5:J11) -> 0
B13: Costs
B14: OPEX / RESCO – operation | D14: 3650000 | E14: 5500000 | F14: 7500000 | G14: 9500000 | H14: 11500000 | I14: 12500000
B15: CAPEX | D15: 75000000 | E15: 68000000 | F15: 85000000 | G15: 102000000 | H15: 102000000 | I15: 68000000 | J15: Annual incremental capacity
B16: BESS | D16: 0 | E16: 200000 | F16: 600000 | G16: 1000000 | H16: 1500000 | I16: 2000000
B17: AMC | D17: 840000 | E17: 1200000 | F17: 1800000 | G17: 2700000 | H17: 3600000 | I17: 4200000
B18: Energy Efficiency | D18: 0 | E18: 300000 | F18: 900000 | G18: 2100000 | H18: 3300000 | I18: 4800000
B19: I-REC | D19: 0 | E19: 29000 | F19: 148000 | G19: 267000 | H19: 374000 | I19: 475000
B20: Total Costs | D20: =SUM(D14:D19) -> 79490000 | E20: =SUM(E14:E19) -> 75229000 | F20: =SUM(F14:F19) -> 95948000 | G20: =SUM(G14:G19) -> 117567000 | H20: =SUM(H14:H19) -> 122274000 | I20: =SUM(I14:I19) -> 91975000
D21: =D20/D12 -> 0.56117983 | E21: =E20/E12 -> 0.52000774 | F21: =F20/F12 -> 0.49929488 | G21: =G20/G12 -> 0.48730415 | H21: =H20/H12 -> 0.44263043 | I21: =I20/I12 -> 0.33851924
B22: Operating Profit | D22: =D12-D20 -> 62158000 | E22: =E12-E20 -> 69440000 | F22: =F12-F20 -> 96219000 | G22: =G12-G20 -> 123693000 | H22: =H12-H20 -> 153970000 | I22: =I12-I20 -> 179723000
B24: KWH Per Annum | D24: =D5/(1000*5) -> 7993.6 | E24: =E5/(1000*5) -> 12045 | F24: =F5/(1000*5) -> 16425 | G24: =G5/(1000*5) -> 20805 | H24: =H5/(1000*5) -> 25185 | I24: =I5/(1000*5) -> 27375
B25: Incremental Kwh | E25: =E24-D24 -> 4051.4 | F25: =F24-E24 -> 4380 | G25: =G24-F24 -> 4380 | H25: =H24-G24 -> 4380 | I25: =I24-H24 -> 2190
B27: CAPEX Prokects (Kwp) | D27: =D6/100000 -> 1000 | E27: =E6/100000 -> 800 | F27: =F6/100000 -> 1000 | G27: =G6/100000 -> 1200 | H27: =H6/100000 -> 1200 | I27: =I6/100000 -> 800
D28: =D14/D5 -> 0.091323058 | E28: =E14/E5 -> 0.091324201 | F28: =F14/F5 -> 0.091324201 | G28: =G14/G5 -> 0.091324201 | H28: =H14/H5 -> 0.091324201 | I28: =I14/I5 -> 0.091324201
D29: =D15/D6 -> 0.75 | E29: =E15/E6 -> 0.85 | F29: =F15/F6 -> 0.85 | G29: =G15/G6 -> 0.85 | H29: =H15/H6 -> 0.85 | I29: =I15/I6 -> 0.85

Sheet OPEX & CAPEX
A1: Dimension | B1: CAPEX Model (Customer-Owned Solar) | C1: OPEX Model (RESCO / IPP-Owned Solar)
A2: Asset Ownership | B2: Customer owns the solar plant | C2: Solar company owns the asset
A3: Typical Customers (Nepal) | B3: Hotels, factories, banks, hospitals, schools, government, NGOs | C3: NEA (utility IPP), large corporates, captive users
A4: Regulatory Interface | B4: Net-metering approval (NEA), AEPC subsidy (if applicable) | C4: NEA PPA approval, grid connection, licensing
A5: Primary Revenue Source | B5: EPC contract payment (one-time) | C5: Electricity sales under long-term PPA
A6: Revenue Pricing (Nepal) | B6: NPR 90,000–120,000 per kWp (rooftop EPC) | C6: PPA tariff: • NEA utility solar: ~NPR 5.94/kWh • Corporate RESCO: NPR 7–10/kWh
A7: Revenue Nature | B7: One-time, project-based | C7: Recurring, annuity-based
A8: Contract Tenure | B8: 3–6 months EPC cycle | C8: 10–25 years
A9: Payment Timeline | B9: Milestone or commissioning-linked | C9: Monthly / quarterly energy billing
A10: Cash Flow Timing | B10: Front-loaded | C10: Back-ended but stable
A11: Typical Annual Yield | B11: Not applicable | C11: ~1,400–1,600 kWh per kWp (Nepal)
A12: Recurring Add-on Revenue | B12: O&M contracts (1–2% of EPC cost per year) | C12: O&M embedded in ownership
... A22: Best Use Case in Nepal | B22: Cash flow generation, market entry | C22: Long-term value creation

Sheet Queries
B2: Queries | C2: No cost of material in FY 2080/81
C3: Investment Details
C4: Details of Intangible Assets
C5: Net Mirroring

Sheet Ratios
B2: ='Historical SOPL'!B2:F2 -> Simple Energy Private Limited
B3: Financial Ratio Analysis
B5: Ratios | C5: FY 2079/80 | D5: FY 2079/80 | E5: ='Historical SOPL'!E6 -> FY 2080/81 | F5: ='Historical SOPL'!F6 -> FY 2081/82
B6: Profitability Ratios
B7: Gross Profit Margin | D7: ='Historical SOPL'!D9/'Historical SOPL'!D7 -> 0.89143888 | E7: ='Historical SOPL'!E9/'Historical SOPL'!E7 -> 1 | F7: ='Historical SOPL'!F9/'Historical SOPL'!F7 -> 0.54927604
B8: EBITDA Margin | D8: ='Historical SOPL'!D14/'Historical SOPL'!D7 -> 0.48854867 | E8: ='Historical SOPL'!E14/'Historical SOPL'!E7 -> 1.1306257 | F8: ='Historical SOPL'!F14/'Historical SOPL'!F7 -> 0.52274917
B9: Net Profit Margin | D9: ='Historical SOPL'!D20/'Historical SOPL'!D7 -> -0.54474992 | E9: ='Historical SOPL'!E20/'Historical SOPL'!E7 -> 0.24083945 | F9: ='Historical SOPL'!F20/'Historical SOPL'!F7 -> 0.3105443
B10: Return on Assets (ROA) | C10: ='Historical SOPL'!C20/'Historical SOFP'!C21 -> -0.069970972 | D10: ='Historical SOPL'!D20/'Historical SOFP'!D21 -> -0.024352811 | E10: ='Historical SOPL'!E20/'Historical SOFP'!E21 -> 0.018715998 | F10: ='Historical SOPL'!F20/'Historical SOFP'!F21 -> 0.098267515
B11: Return on Equity (ROE) | C11: ='Historical SOPL'!C20/'Historical SOFP'!C36 -> -0.081155439 | D11: ='Historical SOPL'!D20/'Historical SOFP'!D36 -> -0.024659232 | E11: ='Historical SOPL'!E20/'Historical SOFP'!E36 -> 0.019088888 | F11: ='Historical SOPL'!F20/'Historical SOFP'!F36 -> 0.10077582
B13: Liquidity Ratios
B14: Current Ratio | C14: ='Historical SOFP'!C20/'Historical SOFP'!C30 -> 0.40989081 | D14: ='Historical SOFP'!D20/'Historical SOFP'!D30 -> 16.176755 | E14: ='Historical SOFP'!E20/'Historical SOFP'!E30 -> 15.357992 | F14: ='Historical SOFP'!F20/'Historical SOFP'!F30 -> 13.008888
B15: Quick Ratio (Acid-Test Ratio) | C15: =('Historical SOFP'!C20-'Historical SOFP'!C14)/'Historical SOFP'!C30 -> 0.40989081 | D15: =('Historical SOFP'!D20-'Historical SOFP'!D14)/'Historical SOFP'!D30 -> 16.176755 | E15: =('Historical SOFP'!E20-'Historical SOFP'!E14)/'Historical SOFP'!E30 -> 15.357992 | F15: =('Historical SOFP'!F20-'Historical SOFP'!F14)/'Historical SOFP'!F30 -> 13.008888
B17: Efficiency Ratios
B18: Inventory Turnover
B19: Inventory Holding Period (Days)
I20: 2079/80 | J20: 2079/80 | K20: 2080/81 | L20: 2081/82
B21: Receivables Turnover | C21: ='Historical SOPL'!C7/'Historical SOFP'!C15 -> 0 | D21: ='Historical SOPL'!D7/'Historical SOFP'!D15 -> 2.027063 | E21: ='Historical SOPL'!E7/'Historical SOFP'!E15 -> 1.8493294 | F21: ='Historical SOPL'!F7/'Historical SOFP'!F15 -> 2.1794898 | H21: NAV Per Share | I21: 92.466662 | J21: 94.007059 | K21: 97.681665 | L21: 108.62882
B22: Receivable collection period (days) | D22: =365/D21 -> 180.06347 | E22: =365/E21 -> 197.36884 | F22: =365/F21 -> 167.47039 | H22: Earning Per Share | I22: -7.5041725 | J22: -2.3181419 | K22: 1.8646344 | L22: 10.947159
B24: Number of shares | C24: ='Historical SOFP'!C32/100 -> 1200000 | D24: ='Historical SOFP'!D32/100 -> 2460000 | E24: ='Historical SOFP'!E32/100 -> 3524440 | F24: ='Historical SOFP'!F32/100 -> 3524440
B26: Profit after Tax | C26: ='Historical SOPL'!C20 -> -9005007 | D26: ='Historical SOPL'!D20 -> -5702629 | E26: ='Historical SOPL'!E20 -> 6571792 | F26: ='Historical SOPL'!F20 -> 38582606
B28: Earning Per share | C28: =C26/C24 -> -7.5041725 | D28: =D26/D24 -> -2.3181419 | E28: =E26/E24 -> 1.8646344 | F28: =F26/F24 -> 10.947159
B30: Net Assets Value (NAV) | C30: ='Historical SOFP'!C36 -> 110959994 | D30: ='Historical SOFP'!D36 -> 231257364 | E30: ='Historical SOFP'!E36 -> 344273166 | F30: ='Historical SOFP'!F36 -> 382855774
B31: NAV per share | C31: =C30/C24 -> 92.466662 | D31: =D30/D24 -> 94.007059 | E31: =E30/E24 -> 97.681665 | F31: =F30/F24 -> 108.62882
B32: Ask Price | F32: 300
B33: Multiple | F33: =F32/F31 -> 2.7616979

Sheet Projects status summary
B2: SN | C2: Sub-Project | D2: City | E2: Capacity (kW) | F2: Capacity (kWp) | G2: Model | H2: Status | I2: Revenue
B3: 1 | C3: Jagadamba Spinning Mills - JSM | D3: Bhairahawa | E3: 500 | F3: 600.24 | G3: OPEX | H3: Operation | I3: =F3*5*1500 -> 4501800 | J3: 1,500 kWh per kWp per year
B4: 2 | C4: Raj Brewery | D4: Parasi | E4: 500 | F4: 599.4 | G4: OPEX | H4: Operation | I4: =F4*5*1500 -> 4495500
B5: 3 | C5: MM Plastics | D5: Biratnagar | E5: 300 | F5: 302.4 | G5: OPEX | H5: Operation | I5: =F5*5*1500 -> 2268000
B6: 4 | C6: MM Polymer | D6: Hetauda | E6: 300 | F6: 301.32 | G6: OPEX | H6: Operation | I6: =F6*5*1500 -> 2259900
B7: 5 | C7: Bhudeko Khadya Udyog - BKU | D7: Godhar | E7: 500 | F7: 604.92 | G7: OPEX | H7: Operation | I7: =F7*5*1500 -> 4536900
B8: 6 | C8: Yak Brewery | D8: Khuritar | E8: 500 | F8: 541.2 | G8: OPEX | H8: Operation | I8: =F8*5*1500 -> 4059000
B9: 7 | C9: Sarbotham Steel Ltd. - SSL | D9: Parwanipur | E9: 500 | F9: 600.6 | G9: OPEX | H9: Operation | I9: =F9*5*1500 -> 4504500
B10: 8 | C10: Jagadamba Tea Processing - JTP | D10: Bhadrapur | E10: 500 | F10: 600.6 | G10: OPEX | H10: Operation | I10: =F10*5*1500 -> 4504500
B11: 9 | C11: Premier Organics Limited - POL | D11: Duhabi | E11: 350 | F11: 447.8 | G11: OPEX | H11: Operation | I11: =F11*5*1500 -> 3358500
B12: 10 | C12: Yeti Brewery | D12: Khairahani | E12: 500 | F12: 600.6 | G12: OPEX | H12: Operation | I12: =F12*5*1500 -> 4504500
B13: 11 | C13: South Asian Beverages - SAB | D13: Parsa | E13: 400 | F13: 528 | G13: OPEX | H13: Operation | I13: =F13*5*1500 -> 3960000
B14: 12 | C14: Nutri Foods | D14: Duhabi | E14: 500 | F14: 615 | G14: CAPEX | H14: Operation | I14: =F14*100000 -> 61500000
B15: 13 | C15: Utsav's House | D15: Lalitpur | E15: 5 | F15: 5 | G15: CAPEX | H15: Operation | I15: =F15*100000 -> 500000
B16: 14 | C16: Jay Shree Polymer | D16: Duhabi | E16: 350 | F16: 478.38 | G16: CAPEX | H16: Operation | I16: =F16*100000 -> 47838000
B17: 15 | C17: Jay Shree PU Tech | D17: Biratnagar | E17: 350 | F17: 478.38 | G17: CAPEX | H17: Operation | I17: =F17*100000 -> 47838000
B18: 16 | C18: Jay Shree Company | D18: Biratnagar | E18: 350 | F18: 422 | G18: CAPEX | H18: Operation | I18: =F18*100000 -> 42200000
B19: 17 | C19: Mainawati Steel | D19: Duhabi | E19: 500 | F19: 670 | G19: OPEX | H19: Operation | I19: =F19*5*1500 -> 5025000
B20: 18 | C20: National Trust for Nature Conservation - NTNC | D20: Lalitpur | E20: 50 | F20: 57 | G20: OPEX | H20: Operation | I20: =F20*8*1500 -> 684000
B21: 19 | C21: Global Auto mobiles | D21: Parsa | E21: 150 | F21: 197 | G21: OPEX | H21: Operation | I21: =F21*8*1500 -> 2364000
B22: 20 | C22: Alexa Life Sciences | D22: Biratnagar | E22: 300 | F22: 401 | G22: OPEX | H22: Operation | I22: =F22*8*1500 -> 4812000
B23: 21 | C23: Fashion Fabrics Export | D23: Biratnagar | E23: 125 | F23: 156 | G23: CAPEX | H23: Operation | I23: =F23*100000 -> 15600000
E24: =SUM(E3:E23) -> 7530 | F24: =SUM(F3:F23) -> 9206.84 | I24: =SUM(I3:I23) -> 271314100
B27: 22 | C27: Industrial rooftop | D27: Duhabi | E27: 250 | F27: 330 | G27: CAPEX | H27: Construction
B28: 23 | C28: Commercial Building | D28: Kathmandu | E28: 20 | F28: 27 | G28: BESS | H28: Designing
B29: 24 | C29: Residential Building | D29: Katmandu | E29: 5 | F29: 5 | G29: BESS | H29: Designing
B30: 25 | C30: ................ | D30: Biratnagar | E30: 50 | F30: 56 | G30: CAPEX | H30: Designing
B31: 26 | C31: ................ | D31: Biratnagar | E31: 200 | F31: 250 | G31: CAPEX | H31: Designing
B32: 27 | C32: ................ | D32: Duhabi | E32: 250 | F32: 310 | G32: OPEX | H32: Designing
B33: 28 | C33: ................ | D33: Bhadrapur | E33: 400 | F33: 500 | G33: OPEX | H33: Designing
B34: 29 | C34: ................ | D34: Bhadrapur | E34: 300 | F34: 500 | G34: OPEX | H34: Designing
B35: 30 | C35: ................ | D35: Biratnagar | E35: 125 | F35: 156 | G35: CAPEX | H35: Designing
B36: 31 | C36: ................ | D36: Biratnagar | E36: 400 | F36: 500 | G36: CAPEX | H36: Designing
B37: 32 | C37: ................ | D37: Chitwan | E37: 125 | F37: 156 | G37: OPEX | H37: Negotiation
B38: 33 | C38: ................ | D38: Kathmandu | E38: 3 | F38: 4.25 | G38: BESS | H38: Negotiation
... B62: 57 | C62: ................ | D62: Chitwan | E62: 400 | F62: 500 | G62: OPEX | H62: Negotiation
C63: Total | E63: =SUM(E3:E62) -> 23198 | F63: =SUM(F3:F62) -> 28776.03

Sheet Pure Energy Limited
B2: Pure Energy Limited
B3: Statement of Profit & Loss | G3: Pure Energy Ltd. operates a 20 MW solar PV power facility in Raniyapur, Khajura Rural Municipality, Banke. The facility consists of two projects: Pure Energy I and Pure Energy II, each generating 10 MW of solar PV energy, totaling a capacity of 20 MW.
B5: Particulars | C5: FY 2081/82 | D5: FY 2080/81
B6: Revenue From Operations | C6: 2.5925692e+08 | D6: 2.007473e+08
B7: Other Income | C7: 15191586 | D7: 3801800
B8: Total Income | C8: =SUM(C6:C7) -> 2.744485e+08 | D8: =SUM(D6:D7) -> 2.045491e+08
B9: Cost of Plant Operations | C9: 14158724 | D9: 9083533.2
B10: Gross Profit | C10: =C8-C9 -> 2.6028978e+08 | D10: =D8-D9 -> 1.9546556e+08
B11: GP Margin | C11: =C10/C6 -> 1.0039839 | D11: =D10/D6 -> 0.97368964
B12: Employee Cost | C12: 11935024 | D12: 8519689
B13: Admin Exp | C13: 9527824.9 | D13: 10684250
B14: Extra Ordinary Expenses | C14: 0 | D14: 4095660
B15: Earning Before Interest, Tax & Depn | C15: =C10-C12-C13-C14 -> 2.3882693e+08 | D15: =D10-D12-D13-D14 -> 1.7216596e+08
B16: EBITDA Margin | C16: =C15/C6 -> 0.92119791 | D16: =D15/D6 -> 0.85762532
B17: Depn | C17: 1.0477449e+08 | D17: 79501977
B18: Earnings Before Interest & Tax | C18: =C15-C17 -> 1.3405244e+08 | D18: =D15-D17 -> 92663988
B19: EBIT Margin | C19: =C18/C6 -> 0.51706409 | D19: =D18/D6 -> 0.4615952
B20: Borrowing Cost | C20: 1.0111403e+08 | D20: 1.1024423e+08
B21: Earnings Before Tax | C21: =C18-C20 -> 32938409 | D21: =D18-D20 -> -17580247
B22: EBT Margin | C22: =C21/C6 -> 0.1270493 | D22: =D21/D6 -> -0.087574016
B23: Bonus | C23: 639580.76
B24: CSR | C24: 319790.38
B25: Earnings Before Tax | C25: =C21-C23-C24 -> 31979038 | D25: =D21-D23-D24 -> -17580247
B26: EBT Margin | C26: =C25/C6 -> 0.12334883 | D26: =D25/D6 -> -0.087574016
